sensor_data_splitter/__init__.py
sensor_data_splitter/dataframe_splitter.py
sensplit/__init__.py
sensplit/dataframe_splitter.py
sensplit-0.0.5.dist-info/LICENSE
sensplit-0.0.5.dist-info/METADATA
sensplit-0.0.5.dist-info/WHEEL
sensplit-0.0.5.dist-info/top_level.txt
sensplit-0.0.5.dist-info/RECORD
